ucp/__init__.py
ucp/ucp.py
ucp/utils.py
ucp-1.0.0.dist-info/DESCRIPTION.rst
ucp-1.0.0.dist-info/METADATA
ucp-1.0.0.dist-info/RECORD
ucp-1.0.0.dist-info/WHEEL
ucp-1.0.0.dist-info/metadata.json
ucp-1.0.0.dist-info/top_level.txt
